plone.formwidget.masterselect-3.0.0-py3.11-nspkg.pth
plone/formwidget/masterselect/__init__.py
plone/formwidget/masterselect/checkbox_input.pt
plone/formwidget/masterselect/configure.zcml
plone/formwidget/masterselect/demo.py
plone/formwidget/masterselect/interfaces.py
plone/formwidget/masterselect/radio_input.pt
plone/formwidget/masterselect/select_input.pt
plone/formwidget/masterselect/setuphandlers.py
plone/formwidget/masterselect/testing.py
plone/formwidget/masterselect/testing.zcml
plone/formwidget/masterselect/widget.py
plone/formwidget/masterselect/profiles/default/jsregistry.xml-dist
plone/formwidget/masterselect/profiles/default/metadata.xml
plone/formwidget/masterselect/profiles/default/registry.xml
plone/formwidget/masterselect/profiles/demo/metadata.xml
plone/formwidget/masterselect/profiles/demo/types.xml
plone/formwidget/masterselect/profiles/demo/types/plone.formwidget.masterselect.demo.xml
plone/formwidget/masterselect/profiles/testupgrades/metadata.xml
plone/formwidget/masterselect/profiles/testupgrades/registry.xml
plone/formwidget/masterselect/static/masterselect.js
plone/formwidget/masterselect/tests/__init__.py
plone/formwidget/masterselect/tests/test_fields.py
plone/formwidget/masterselect/tests/test_intergration.py
plone/formwidget/masterselect/tests/test_robot.py
plone/formwidget/masterselect/tests/test_setup.py
plone/formwidget/masterselect/tests/test_upgrade_steps.py
plone/formwidget/masterselect/tests/robot/test_masterselect_demo.robot
plone/formwidget/masterselect/upgrades/5.zcml
plone/formwidget/masterselect/upgrades/__init__.py
plone/formwidget/masterselect/upgrades/configure.zcml
plone/formwidget/masterselect/upgrades/5/metadata.txt
plone/formwidget/masterselect/upgrades/5/registry.xml
plone.formwidget.masterselect-3.0.0.dist-info/METADATA
plone.formwidget.masterselect-3.0.0.dist-info/WHEEL
plone.formwidget.masterselect-3.0.0.dist-info/entry_points.txt
plone.formwidget.masterselect-3.0.0.dist-info/namespace_packages.txt
plone.formwidget.masterselect-3.0.0.dist-info/top_level.txt
plone.formwidget.masterselect-3.0.0.dist-info/RECORD
