Metadata-Version: 2.1
Name: plone.formwidget.masterselect
Version: 3.0.0
Summary: A z3c.form widget that controls the vocabulary or display of other fields on an edit page
Home-page: https://github.com/collective/plone.formwidget.masterselect
Author: Jason Mehring
Author-email: nrgaway@yahoo.com
License: GPL
Keywords: plone widget
Classifier: Development Status :: 5 - Production/Stable
Classifier: Environment :: Web Environment
Classifier: Framework :: Plone
Classifier: Framework :: Plone :: 5.2
Classifier: Intended Audience :: End Users/Desktop
Classifier: License :: OSI Approved :: GNU General Public License (GPL)
Classifier: Operating System :: OS Independent
Classifier: Programming Language :: JavaScript
Classifier: Programming Language :: Python
Classifier: Programming Language :: Python :: 3.8
Classifier: Topic :: Software Development :: Libraries :: Python Modules
Classifier: Topic :: Software Development :: Widget Sets
Requires-Dist: plone.supermodel
Requires-Dist: plone.z3cform
Requires-Dist: Products.CMFPlone
Requires-Dist: setuptools
Requires-Dist: z3c.form
Requires-Dist: zope.component
Requires-Dist: zope.schema
Provides-Extra: test
Requires-Dist: plone.app.dexterity ; extra == 'test'
Requires-Dist: plone.app.robotframework ; extra == 'test'
Requires-Dist: plone.app.testing[robot] >=4.2.2 ; extra == 'test'
Requires-Dist: plone.registry ; extra == 'test'
Requires-Dist: Products.GenericSetup ; extra == 'test'
